ahrs8p/__init__.py
ahrs8p/ahrs8p.py
ahs8p-0.0.1.dist-info/METADATA
ahs8p-0.0.1.dist-info/WHEEL
ahs8p-0.0.1.dist-info/top_level.txt
ahs8p-0.0.1.dist-info/zip-safe
ahs8p-0.0.1.dist-info/RECORD
